wuji/__init__.py
wuji/Evaluator/Classification.py
wuji/Evaluator/EventDetector.py
wuji/Evaluator/NightlySleepMetrics.py
wuji/Evaluator/__init__.py
wuji/Preprocessor/__init__.py
wuji/Preprocessor/signal.py
wuji/Reader/__init__.py
wuji/Reader/utils.py
wuji/Reader/Annotation/Base.py
wuji/Reader/Annotation/HSP.py
wuji/Reader/Annotation/NSRR.py
wuji/Reader/Annotation/Philips.py
wuji/Reader/Annotation/__init__.py
wuji/Reader/Annotation/compumedics.py
wuji/Reader/Annotation/mnc.py
wuji/Reader/Annotation/nchsdb.py
wuji/Reader/Annotation/stages.py
wuji/Reader/EDF/Base.py
wuji/Reader/EDF/Compumedics.py
wuji/Reader/EDF/HSP.py
wuji/Reader/EDF/NSRR.py
wuji/Reader/EDF/Philips.py
wuji/Reader/EDF/__init__.py
wuji/Reader/EDF/mne_reader.py
wuji/algo/__init__.py
wuji/algo/Oxygen/__init__.py
wuji/algo/Oxygen/desaturation_wrapper.py
wuji/algo/Oxygen/detect_oxygen_desaturation.py
wuji/algo/Oxygen/obm/_ErrorHandler.py
wuji/algo/Oxygen/obm/_ResultsClasses.py
wuji/algo/Oxygen/obm/__init__.py
wuji/algo/Oxygen/obm/desat.py
wuji/biosignal_transformer/__init__.py
wuji/biosignal_transformer/utils.py
wuji/biosignal_transformer/bcg/__init__.py
wuji/biosignal_transformer/bcg/bcg2timefreq.py
wuji/biosignal_transformer/eeg/__init__.py
wuji/biosignal_transformer/eeg/eeg2timefreq.py
wuji/biosignal_transformer/heartbeat/__init__.py
wuji/biosignal_transformer/heartbeat/xxi2hr.py
wuji/examples/__init__.py
wuji/examples/detect_OD_events.py
wuji/examples/eval_classifier.py
wuji/examples/eval_event_detector.py
wuji/examples/eval_nightly_sleep_metrics.py
wuji/examples/read_edf_of_Philips.py
wuji/parser/__init__.py
wuji/parser/hierarchical_yaml.py
wuji/sed_eval/__init__.py
wuji/sed_eval/audio_tag.py
wuji/sed_eval/io.py
wuji/sed_eval/metric.py
wuji/sed_eval/scene.py
wuji/sed_eval/sound_event.py
wuji/sed_eval/test.py
wuji/sed_eval/util/__init__.py
wuji/sed_eval/util/event_list.py
wuji/sed_eval/util/event_matching.py
wuji/sed_eval/util/event_roll.py
wuji/sed_eval/util/scene_list.py
wuji/tools/__init__.py
wuji-0.1.106.dist-info/METADATA
wuji-0.1.106.dist-info/WHEEL
wuji-0.1.106.dist-info/top_level.txt
wuji-0.1.106.dist-info/RECORD
