Metadata-Version: 2.1
Name: wuji
Version: 0.1.106
Requires-Dist: pandas
Requires-Dist: mne
Requires-Dist: xmltodict
Requires-Dist: neurokit2
Requires-Dist: h5py
